midjourney_mcp/__main__.py
midjourney_mcp/midjourney.py
midjourney_mcp-0.1.1.dist-info/licenses/LICENSE
midjourney_mcp-0.1.1.dist-info/METADATA
midjourney_mcp-0.1.1.dist-info/WHEEL
midjourney_mcp-0.1.1.dist-info/entry_points.txt
midjourney_mcp-0.1.1.dist-info/top_level.txt
midjourney_mcp-0.1.1.dist-info/RECORD
