Metadata-Version: 2.4
Name: midjourney-mcp
Version: 0.1.1
Summary: A MCP server for generating images with Midjourney
License-Expression: GPL-3.0
Requires-Python: >=3.10
License-File: LICENSE
Requires-Dist: curl-cffi>=0.10.0
Requires-Dist: httpx>=0.28.1
Requires-Dist: mcp[cli]>=1.6.0
Dynamic: license-file
